BFG_Y2H-0.1.0.data/scripts/bfg
BFG_Y2H-0.1.0.data/scripts/rc
bfg_analysis/HSR_main.py
bfg_analysis/__init__.py
bfg_analysis/alignment.py
bfg_analysis/create_fasta.py
bfg_analysis/evaluation.py
bfg_analysis/main.py
bfg_analysis/noz_score.py
bfg_analysis/plot.py
bfg_analysis/read_counts.py
bfg_analysis/read_output.py
bfg_analysis/score.py
bfg_analysis/score_main.py
bfg_analysis/supplements.py
bfg_analysis/data/logging.conf
BFG_Y2H-0.1.0.dist-info/LICENSE
BFG_Y2H-0.1.0.dist-info/METADATA
BFG_Y2H-0.1.0.dist-info/WHEEL
BFG_Y2H-0.1.0.dist-info/top_level.txt
BFG_Y2H-0.1.0.dist-info/RECORD
