Metadata-Version: 2.1
Name: BFG-Y2H
Version: 0.1.0
Summary: Analysis scripts for BFG-Y2H data
Home-page: https://github.com/RyogaLi/BFG_Y2H
Author: ROUJIA LI
Author-email: roujia.li@mail.utoronto.ca
License: UNKNOWN
Platform: UNKNOWN
Classifier: Development Status :: 3 - Alpha
Classifier: Intended Audience :: Developers
Classifier: Topic :: Software Development :: Build Tools
Classifier: License :: OSI Approved :: MIT License
Classifier: Programming Language :: Python :: 3.6
Classifier: Programming Language :: Python :: 3.7
Classifier: Programming Language :: Python :: 3.8
Requires-Python: >=3.6
Requires-Dist: pandas
Requires-Dist: seaborn
Requires-Dist: numpy
Requires-Dist: biopython
